ProgramizKotlinJiaochengChuyi/README.md
ProgramizKotlinJiaochengChuyi/__init__.py
ProgramizKotlinJiaochengChuyi/__main__.py
ProgramizKotlinJiaochengChuyi/file.epub
ProgramizKotlinJiaochengChuyi/index.html
ProgramizKotlinJiaochengChuyi/css/__init__.py
ProgramizKotlinJiaochengChuyi/css/annotations.css
ProgramizKotlinJiaochengChuyi/css/main.css
ProgramizKotlinJiaochengChuyi/css/normalize.css
ProgramizKotlinJiaochengChuyi/css/popup.css
ProgramizKotlinJiaochengChuyi/font/__init__.py
ProgramizKotlinJiaochengChuyi/font/fontello.eot
ProgramizKotlinJiaochengChuyi/font/fontello.svg
ProgramizKotlinJiaochengChuyi/font/fontello.ttf
ProgramizKotlinJiaochengChuyi/font/fontello.woff
ProgramizKotlinJiaochengChuyi/img/__init__.py
ProgramizKotlinJiaochengChuyi/img/annotator-glyph-sprite.png
ProgramizKotlinJiaochengChuyi/img/annotator-icon-sprite.png
ProgramizKotlinJiaochengChuyi/img/apple-touch-icon.png
ProgramizKotlinJiaochengChuyi/img/cancelfullscreen.png
ProgramizKotlinJiaochengChuyi/img/close.png
ProgramizKotlinJiaochengChuyi/img/fullscreen.png
ProgramizKotlinJiaochengChuyi/img/loader.gif
ProgramizKotlinJiaochengChuyi/img/menu-icon.png
ProgramizKotlinJiaochengChuyi/img/save.png
ProgramizKotlinJiaochengChuyi/img/saved.png
ProgramizKotlinJiaochengChuyi/img/settings-s.png
ProgramizKotlinJiaochengChuyi/img/settings.png
ProgramizKotlinJiaochengChuyi/img/star.png
ProgramizKotlinJiaochengChuyi/js/__init__.py
ProgramizKotlinJiaochengChuyi/js/epub.js
ProgramizKotlinJiaochengChuyi/js/epub.min.js
ProgramizKotlinJiaochengChuyi/js/epub.min.map
ProgramizKotlinJiaochengChuyi/js/hooks.min.js
ProgramizKotlinJiaochengChuyi/js/hooks.min.map
ProgramizKotlinJiaochengChuyi/js/reader.js
ProgramizKotlinJiaochengChuyi/js/reader.js.map
ProgramizKotlinJiaochengChuyi/js/reader.min.js
ProgramizKotlinJiaochengChuyi/js/reader.min.map
ProgramizKotlinJiaochengChuyi/js/hooks/__init__.py
ProgramizKotlinJiaochengChuyi/js/hooks/extensions/__init__.py
ProgramizKotlinJiaochengChuyi/js/hooks/extensions/highlight.js
programiz_kotlin_jiaocheng_chuyi-2024.3.5.0.dist-info/METADATA
programiz_kotlin_jiaocheng_chuyi-2024.3.5.0.dist-info/WHEEL
programiz_kotlin_jiaocheng_chuyi-2024.3.5.0.dist-info/entry_points.txt
programiz_kotlin_jiaocheng_chuyi-2024.3.5.0.dist-info/top_level.txt
programiz_kotlin_jiaocheng_chuyi-2024.3.5.0.dist-info/RECORD
